LICENSE
MANIFEST.in
README.rst
setup.cfg
setup.py
testing.ini
almir/__init__.py
almir/forms.py
almir/meta.py
almir/models.py
almir/views.py
almir.egg-info/PKG-INFO
almir.egg-info/SOURCES.txt
almir.egg-info/dependency_links.txt
almir.egg-info/entry_points.txt
almir.egg-info/not-zip-safe
almir.egg-info/requires.txt
almir.egg-info/top_level.txt
almir/lib/__init__.py
almir/lib/bacula_base64.py
almir/lib/bconsole.py
almir/lib/console_commands.py
almir/lib/sqlalchemy_custom_types.py
almir/lib/sqlalchemy_declarative_reflection.py
almir/lib/sqlalchemy_lowercase_inspector.py
almir/lib/utils.py
almir/scripts/__init__.py
almir/scripts/configure_deploy.py
almir/scripts/parse_console_commands.py
almir/static/bootstrap/bootstrap-responsive.min.css
almir/static/bootstrap/bootstrap.min.css
almir/static/bootstrap/bootstrap.min.js
almir/static/bootstrap/img/glyphicons-halflings-white.png
almir/static/bootstrap/img/glyphicons-halflings.png
almir/static/css/main.less
almir/static/datatables/TableTools.min.js
almir/static/datatables/bootstrap.css
almir/static/datatables/bootstrap.js
almir/static/datatables/copy_cvs_xls_pdf.swf
almir/static/datatables/jquery.dataTables.min.js
almir/static/datatables/type_filesize.js
almir/static/datatables/type_hidden_numeric_data.js
almir/static/datatables/images/Sorting icons.psd
almir/static/datatables/images/back_disabled.png
almir/static/datatables/images/back_enabled.png
almir/static/datatables/images/back_enabled_hover.png
almir/static/datatables/images/favicon.ico
almir/static/datatables/images/forward_disabled.png
almir/static/datatables/images/forward_enabled.png
almir/static/datatables/images/forward_enabled_hover.png
almir/static/datatables/images/sort_asc.png
almir/static/datatables/images/sort_asc_disabled.png
almir/static/datatables/images/sort_both.png
almir/static/datatables/images/sort_desc.png
almir/static/datatables/images/sort_desc_disabled.png
almir/static/images/favicon.ico
almir/static/js/html5.js
almir/static/js/jquery-1.7.1.min.js
almir/static/js/less-1.1.5.min.js
almir/static/js/main.js
almir/templates/about.jinja2
almir/templates/base.jinja2
almir/templates/client_detail.jinja2
almir/templates/client_list.jinja2
