Metadata-Version: 1.1
Name: almir
Version: 0.1.8
Summary: Almir is a Bacula (backup solution) web interface written in Python.
Home-page: UNKNOWN
Author: Domen Kozar
Author-email: domen@dev.si
License: UNKNOWN
Keywords: web pyramid bacula administration
Platform: UNKNOWN
Classifier: Programming Language :: Python
Classifier: Framework :: Pylons
Classifier: Topic :: Internet :: WWW/HTTP
Classifier: Topic :: Internet :: WWW/HTTP :: WSGI :: Application
Classifier: Topic :: System :: Archiving :: Backup
Classifier: License :: OSI Approved :: GNU General Public License (GPL)
